[
  {
    "title": "خدمات پس از فروش یکپارچه",
    "subtitle": "در کنار شبکه نمایندگان",
    "description": "پوشش سراسری و پشتیبانی تخصصی برای تعمیرات و تامین قطعات برندهای لوازم خانگی.",
    "ctaLabel": "همکاری با نمایندگی‌ها",
    "ctaLink": "/representatives/signup",
    "image": "/images/slides/1.jpg"
  },
  {
    "title": "پوشش سراسری خدمات پس از فروش",
    "subtitle": "همراهی مشتریان تا پایان گارانتی",
    "description": "مرکز تماس و شبکه سرویس برای پیگیری تعمیرات، تامین قطعه و پاسخگویی سریع در سراسر کشور.",
    "ctaLabel": "بررسی وضعیت گارانتی",
    "ctaLink": "/warranty/check",
    "image": "/images/slides/2.jpg"
  },
  {
    "title": "آموزش و مستندسازی تعمیرات",
    "subtitle": "دانش فنی به‌روز برای تکنسین‌ها",
    "description": "مستندات و ویدیوهای آموزشی برای نمایندگان تا کار استاندارد و سریع انجام شود و کیفیت سرویس یکنواخت بماند.",
    "ctaLabel": "مشاهده آموزش‌ها",
    "ctaLink": "/education",
    "image": "/images/slides/3.jpg"
  },
  {
    "title": "مدیریت محصولات و سیاست‌های گارانتی",
    "subtitle": "هم‌راستا با برند و نمایندگی",
    "description": "محصولات فعال، وضعیت گارانتی و سیاست‌های خدمات را یکجا ببینید، ثبت کنید و برای نمایندگان به‌روز نگه دارید.",
    "ctaLabel": "مشاهده محصولات",
    "ctaLink": "/products",
    "image": "/images/slides/4.jpg"
  }
]
